Workbook

Sheet Resumo
A1: Proposta de Abastecimento — EMEFARMA (RJ)
A3: Linha Vitamedic cadastrada no cliente · base de estoque 20/08/2026 · Vitamedic Trade Marketing
A5: Premissas do modelo (editaveis)
A6: Aporte total proposto (R$) | B6: 450000
A7: DDE-alvo pos-compra (dias) | B7: 120
A8: Teto de concentracao por SKU (%) | B8: 0.2
A9: Cobertura maxima elegivel p/ compra (dias) | B9: 180
A10: * As colunas J-M da aba Proposta_SKU foram calculadas fora da planilha (modelo de alocacao com teto por SKU) e entram como valores em I; mudar as premissas acima nao re-executa o modelo de alocacao automaticamente, mas recalcula elegibilidade e todos os totais.
A12: Resultado da proposta
A13: =SUM(Proposta_SKU!J5:J134) | B13: =SUM(Proposta_SKU!E5:E134) | C13: =SUM(Proposta_SKU!L5:L134) | D13: =COUNTIF(Proposta_SKU!I5:I134,">0")
A15: Compra proposta | B15: Estoque atual (130 SKUs) | C15: Estoque projetado | D15: SKUs contemplados
A17: Cobertura media ponderada (DDE) - SKUs com compra > 0
A18: Antes do aporte | B18: =SUMPRODUCT((Proposta_SKU!I5:I134>0)*Proposta_SKU!F5:F134*Proposta_SKU!E5:E134)/SUMPRODUCT((Proposta_SKU!I5:I134>0)*Proposta_SKU!E5:E134)
A19: Depois do aporte | B19: =SUMPRODUCT((Proposta_SKU!I5:I134>0)*Proposta_SKU!M5:M134*Proposta_SKU!L5:L134)/SUMPRODUCT((Proposta_SKU!I5:I134>0)*Proposta_SKU!L5:L134)
A21: Distribuicao do aporte por tier
A22: Tier | B22: SKUs | C22: Estoque atual | D22: Compra proposta | E22: Estoque final | F22: Regra aplicada
A23: Saudável | B23: =COUNTIF(Proposta_SKU!$B$5:$B$134,"Saudável") | C23: =SUMIF(Proposta_SKU!$B$5:$B$134,"Saudável",Proposta_SKU!$E$5:$E$134) | D23: =SUMIF(Proposta_SKU!$B$5:$B$134,"Saudável",Proposta_SKU!$J$5:$J$134) | E23: =SUMIF(Proposta_SKU!$B$5:$B$134,"Saudável",Proposta_SKU!$L$5:$L$134) | F23: < 60 dias - giro rapido, repor normalmente
A24: Atenção | B24: =COUNTIF(Proposta_SKU!$B$5:$B$134,"Atenção") | C24: =SUMIF(Proposta_SKU!$B$5:$B$134,"Atenção",Proposta_SKU!$E$5:$E$134) | D24: =SUMIF(Proposta_SKU!$B$5:$B$134,"Atenção",Proposta_SKU!$J$5:$J$134) | E24: =SUMIF(Proposta_SKU!$B$5:$B$134,"Atenção",Proposta_SKU!$L$5:$L$134) | F24: 60-120 dias - repor ate perto do DDE-alvo
A25: Alto | B25: =COUNTIF(Proposta_SKU!$B$5:$B$134,"Alto") | C25: =SUMIF(Proposta_SKU!$B$5:$B$134,"Alto",Proposta_SKU!$E$5:$E$134) | D25: =SUMIF(Proposta_SKU!$B$5:$B$134,"Alto",Proposta_SKU!$J$5:$J$134) | E25: =SUMIF(Proposta_SKU!$B$5:$B$134,"Alto",Proposta_SKU!$L$5:$L$134) | F25: 120-180 dias - repor so o que falta ate o alvo
A26: Crítico | B26: =COUNTIF(Proposta_SKU!$B$5:$B$134,"Crítico") | C26: =SUMIF(Proposta_SKU!$B$5:$B$134,"Crítico",Proposta_SKU!$E$5:$E$134) | D26: =SUMIF(Proposta_SKU!$B$5:$B$134,"Crítico",Proposta_SKU!$J$5:$J$134) | E26: =SUMIF(Proposta_SKU!$B$5:$B$134,"Crítico",Proposta_SKU!$L$5:$L$134) | F26: 180-365 dias - SEM compra
A27: Zumbi | B27: =COUNTIF(Proposta_SKU!$B$5:$B$134,"Zumbi") | C27: =SUMIF(Proposta_SKU!$B$5:$B$134,"Zumbi",Proposta_SKU!$E$5:$E$134) | D27: =SUMIF(Proposta_SKU!$B$5:$B$134,"Zumbi",Proposta_SKU!$J$5:$J$134) | E27: =SUMIF(Proposta_SKU!$B$5:$B$134,"Zumbi",Proposta_SKU!$L$5:$L$134) | F27: > 365 dias - SEM compra
A28: Lançamento | B28: =COUNTIF(Proposta_SKU!$B$5:$B$134,"Lançamento") | C28: =SUMIF(Proposta_SKU!$B$5:$B$134,"Lançamento",Proposta_SKU!$E$5:$E$134) | D28: =SUMIF(Proposta_SKU!$B$5:$B$134,"Lançamento",Proposta_SKU!$J$5:$J$134) | E28: =SUMIF(Proposta_SKU!$B$5:$B$134,"Lançamento",Proposta_SKU!$L$5:$L$134) | F28: Energrip C Pop Kd - SEM compra, ver aba dedicada
A30: Investimento complementar provisionado
A31: Ver aba Acoes_Investimento para o detalhamento linha a linha.
A32: Total provisionado | B32: =Acoes_Investimento!B17
A34: Nota metodologica
A35: O aporte e alocado por DDE-alvo: cada SKU elegivel (cobertura atual abaixo do teto elegivel e fora da linha de lancamento) recebe compra suficiente para chegar perto do DDE-alvo, respeitando um teto de concentracao por SKU (evita apostar o aporte inteiro em 1-2 produtos). SKUs em Critico e Zumbi ficam com compra zero - comprar mais ali pioraria o problema ja mapeado no dossie (secoes 12 e 17). DIPIRONA 1G 10CPD esta a 0,02 dia de cobertura (59 un em estoque para ~16.800 un/mes de giro) e atinge o teto de concentracao (20%) - e a prioridade de reposicao de urgencia desta proposta.

Sheet Proposta_SKU
A1: Proposta por SKU — linha Vitamedic cadastrada no EMEFARMA (RJ)
A2: Colunas A-G vem da base de estoque de 20/08/2026 (Custo Rep, Estoque Total Un, Cobertura, Media Venda Un). Coluna I (Compra proposta) e a decisao do modelo de alocacao por DDE-alvo - editavel linha a linha; as colunas J a M recalculam automaticamente.
A4: Produto | B4: Tier | C4: Custo Rep (R$/un) | D4: Estoque atual (un) | E4: Estoque atual (R$) | F4: DDE atual | G4: Venda media (un/mes) | H4: Elegivel p/ compra | I4: Compra proposta (un) | J4: Compra proposta (R$) | K4: Estoque final (un) | L4: Estoque final (R$) | M4: DDE final | N4: Observacao
A5: ANLODIPINO 5MG 30CPD G VTC | B5: Alto | C5: 1.3045 | D5: 33868 | E5: =C5*D5 | F5: 158.3 | G5: 6409 | H5: =IF(AND(F5<Resumo!$B$8,B5<>"Lançamento",G5>0),"Sim","Não") | I5: 0 | J5: =I5*C5 | K5: =D5+I5 | L5: =K5*C5 | M5: =IF(G5>0,K5/(G5/30),"—") | N5: Ja proximo ou acima do DDE-alvo - sem compra necessaria.
A6: NIMESULIDA 100MG 12CPD G VTC | B6: Alto | C6: 1.2952 | D6: 22015 | E6: =C6*D6 | F6: 170.9 | G6: 3863 | H6: =IF(AND(F6<Resumo!$B$8,B6<>"Lançamento",G6>0),"Sim","Não") | I6: 0 | J6: =I6*C6 | K6: =D6+I6 | L6: =K6*C6 | M6: =IF(G6>0,K6/(G6/30),"—") | N6: Ja proximo ou acima do DDE-alvo - sem compra necessaria.
A7: ATENOLOL 25MG 30CPD G VTC | B7: Alto | C7: 1.2106 | D7: 10793 | E7: =C7*D7 | F7: 147.4 | G7: 2196 | H7: =IF(AND(F7<Resumo!$B$8,B7<>"Lançamento",G7>0),"Sim","Não") | I7: 0 | J7: =I7*C7 | K7: =D7+I7 | L7: =K7*C7 | M7: =IF(G7>0,K7/(G7/30),"—") | N7: Ja proximo ou acima do DDE-alvo - sem compra necessaria.
A8: IBUPROFENO 100MG/ML SUSP ORAL 20ML G VTC | B8: Alto | C8: 2.4881 | D8: 2912 | E8: =C8*D8 | F8: 132 | G8: 662 | H8: =IF(AND(F8<Resumo!$B$8,B8<>"Lançamento",G8>0),"Sim","Não") | I8: 0 | J8: =I8*C8 | K8: =D8+I8 | L8: =K8*C8 | M8: =IF(G8>0,K8/(G8/30),"—") | N8: Ja proximo ou acima do DDE-alvo - sem compra necessaria.
A9: ENERGRIP C+ ZINCO 1G+10MG 10CPD EFEV VTC | B9: Alto | C9: 4.0006 | D9: 2259 | E9: =C9*D9 | F9: 167.7 | G9: 404 | H9: =IF(AND(F9<Resumo!$B$8,B9<>"Lançamento",G9>0),"Sim","Não") | I9: 0 | J9: =I9*C9 | K9: =D9+I9 | L9: =K9*C9 | M9: =IF(G9>0,K9/(G9/30),"—") | N9: Ja proximo ou acima do DDE-alvo - sem compra necessaria.
A10: IVERMECTINA 6MG 2CPD G VTC | B10: Alto | C10: 2.4009 | D10: 1689 | E10: =C10*D10 | F10: 121.3 | G10: 417 | H10: =IF(AND(F10<Resumo!$B$8,B10<>"Lançamento",G10>0),"Sim","Não") | I10: 0 | J10: =I10*C10 | K10: =D10+I10 | L10: =K10*C10 | M10: =IF(G10>0,K10/(G10/30),"—") | N10: Ja proximo ou acima do DDE-alvo - sem compra necessaria.
A11: CICLOBENZAPRINA 10MG 15CPD G VTC | B11: Alto | C11: 3.0201 | D11: 1196 | E11: =C11*D11 | F11: 162.7 | G11: 220 | H11: =IF(AND(F11<Resumo!$B$8,B11<>"Lançamento",G11>0),"Sim","Não") | I11: 0 | J11: =I11*C11 | K11: =D11+I11 | L11: =K11*C11 | M11: =IF(G11>0,K11/(G11/30),"—") | N11: Ja proximo ou acima do DDE-alvo - sem compra necessaria.
A12: IBUPROFENO 600MG 10CPD G VTC | B12: Alto | C12: 7.9399 | D12: 934 | E12: =C12*D12 | F12: 143 | G12: 196 | H12: =IF(AND(F12<Resumo!$B$8,B12<>"Lançamento",G12>0),"Sim","Não") | I12: 0 | J12: =I12*C12 | K12: =D12+I12 | L12: =K12*C12 | M12: =IF(G12>0,K12/(G12/30),"—") | N12: Ja proximo ou acima do DDE-alvo - sem compra necessaria.
A13: ENERGRIP C TRIP ACAO 1G+10CPD EFERV VTC | B13: Alto | C13: 4.6199 | D13: 919 | E13: =C13*D13 | F13: 154 | G13: 179 | H13: =IF(AND(F13<Resumo!$B$8,B13<>"Lançamento",G13>0),"Sim","Não") | I13: 0 | J13: =I13*C13 | K13: =D13+I13 | L13: =K13*C13 | M13: =IF(G13>0,K13/(G13/30),"—") | N13: Ja proximo ou acima do DDE-alvo - sem compra necessaria.
A14: GUAKOEXPEC 0,1ML/ML XPE 150ML VTC | B14: Alto | C14: 6.7286 | D14: 573 | E14: =C14*D14 | F14: 140.9 | G14: 122 | H14: =IF(AND(F14<Resumo!$B$8,B14<>"Lançamento",G14>0),"Sim","Não") | I14: 0 | J14: =I14*C14 | K14: =D14+I14 | L14: =K14*C14 | M14: =IF(G14>0,K14/(G14/30),"—") | N14: Ja proximo ou acima do DDE-alvo - sem compra necessaria.
A15: ENERGRIP C IMUNO ENERGY 16CDP EFERV VTC | B15: Alto | C15: 11.8398 | D15: 266 | E15: =C15*D15 | F15: 169.8 | G15: 47 | H15: =IF(AND(F15<Resumo!$B$8,B15<>"Lançamento",G15>0),"Sim","Não") | I15: 0 | J15: =I15*C15 | K15: =D15+I15 | L15: =K15*C15 | M15: =IF(G15>0,K15/(G15/30),"—") | N15: Ja proximo ou acima do DDE-alvo - sem compra necessaria.
A16: GLICOMET 500MG 30CPD VTC | B16: Alto | C16: 3.8436 | D16: 237 | E16: =C16*D16 | F16: 151.3 | G16: 47 | H16: =IF(AND(F16<Resumo!$B$8,B16<>"Lançamento",G16>0),"Sim","Não") | I16: 0 | J16: =I16*C16 | K16: =D16+I16 | L16: =K16*C16 | M16: =IF(G16>0,K16/(G16/30),"—") | N16: Ja proximo ou acima do DDE-alvo - sem compra necessaria.
... A133: ATENOLOL+CLORTAL 100+25MG 30CPD G VTC | B133: Zumbi | C133: 8.5132 | D133: 47 | E133: =C133*D133 | F133: 705 | G133: 2 | H133: =IF(AND(F133<Resumo!$B$8,B133<>"Lançamento",G133>0),"Sim","Não") | I133: 0 | J133: =I133*C133 | K133: =D133+I133 | L133: =K133*C133 | M133: =IF(G133>0,K133/(G133/30),"—") | N133: Cobertura acima do teto elegivel - sem compra. Ver secao 12/17 do dossie.
A134: KIT GLUCOLEADER APARELH+EST+BATERIA VTC | B134: Zumbi | C134: 25.1291 | D134: 19 | E134: =C134*D134 | G134: 0 | H134: =IF(AND(F134<Resumo!$B$8,B134<>"Lançamento",G134>0),"Sim","Não") | I134: 0 | J134: =I134*C134 | K134: =D134+I134 | L134: =K134*C134 | M134: =IF(G134>0,K134/(G134/30),"—") | N134: Cobertura acima do teto elegivel - sem compra. Ver secao 12/17 do dossie.
A135: TOTAL (130 SKUs) | E135: =SUM(E5:E134) | I135: =SUM(I5:I134) | J135: =SUM(J5:J134) | L135: =SUM(L5:L134)

Sheet Energrip_PopKd
A1: Energrip C Pop Kd — plano de ativação (lançamento)
A4: Produto de lançamento, sem histórico de venda consolidado — a cobertura de 7.920 e 3.195 dias apurada no dossiê (seções 12/17) é um artefato de dividir estoque de arranque por giro quase nulo, não um sinal de encalhe. Diferente do Forday (linha madura em queda), aqui o gargalo é ativação, não excesso de estoque. Por isso esta proposta NÃO aloca compra adicional para o Pop Kd — o estoque já comprado (741 un, R$ 27.847 a custo) é suficiente para lançar; o investimento vai para fazer girar.
A9: Estoque atual da linha
A10: SKU | B10: Custo Rep (R$/un) | C10: Estoque (un) | D10: Estoque (R$) | E10: Cobertura (DDE) | F10: Venda un/mês | G10: Leitura
A11: Energrip C Pop Kd Laranja disp 500mg | B11: 37.58 | C11: 528 | D11: =B11*C11 | E11: =IF(F11>0,C11/(F11/30),"—") | F11: 3 | G11: 7.920 d — 3 un/mês vendidas
A12: Energrip C Pop Kd Morango disp 250mg | B12: 37.58 | C12: 213 | D12: =B12*C12 | E12: =IF(F12>0,C12/(F12/30),"—") | F12: 7 | G12: 3.195 d — 7 un/mês vendidas
A13: Total | C13: =SUM(C11:C12) | D13: =SUM(D11:D12)
A15: Dimensionamento da ativação (premissas editáveis)
A16: PDVs ativos EMEFARMA RJ (últ. mês fechado) | B16: 1834
A17: % de PDVs prioritários no lançamento (curva A/B) | B17: 0.2
A18: Custo de degustação/amostra por PDV (R$) | B18: 25
A19: Custo de material de exposição por PDV (R$) | B19: 18
A20: Incentivo à força de vendas (90 dias, R$) | B20: 5000
A21: Treinamento/briefing da equipe do distribuidor (R$) | B21: 2000
A23: PDVs prioritários (lançamento) | B23: =ROUND(B16*B17,0)
A24: Degustação/amostragem | B24: =B23*B18
A25: Material de exposição (display/wobbler) | B25: =B23*B19
A26: Incentivo à força de vendas | B26: =B20
A27: Treinamento/briefing | B27: =B21
A28: Total ativação Pop Kd | B28: =SUM(B24:B27)
A30: Checkpoint de performance
A31: Revisão em 90 dias: se o giro da linha não atingir ao menos 60 un/mês combinadas (referência conservadora, ~4x o mix atual dos dois sabores), reavaliar sortimento por PDV antes de qualquer nova compra — não repetir o aporte automaticamente. Se atingir a meta, entra no próximo ciclo de reposição pelo mesmo modelo de DDE-alvo usado no restante da linha (aba Proposta_SKU).

Sheet Acoes_Investimento
A1: Ações complementares e investimento provisionado
A4: Objetivo: dar ao distribuidor confiança de que o aporte de R$ 450 mil vai girar, não empilhar. Três frentes: (1) proteger o giro do que já vende bem e acabou de ser reforçado, (2) ativar o lançamento Energrip Pop Kd, e (3) uma reserva de contingência — giro garantido — caso alguma linha não performe como esperado.
A8: Premissas (editáveis)
A9: % giro pós-reforço sobre o aporte | B9: 0.05
A10: % contingência (giro garantido) sobre o aporte | B10: 0.05
A12: Ação | B12: Investimento (R$) | C12: Tipo | D12: Racional
A13: Campanha de giro pós-reforço (SKUs replenished) | B13: =Resumo!B13*B9 | C13: Ativo | D13: Garante que o volume comprado saia do CD - checkout incentive/degustação nos PDVs que mais crescem.
A14: Ativação Energrip C Pop Kd (lançamento) | B14: =Energrip_PopKd!B28 | C14: Ativo | D14: Detalhamento completo na aba Energrip_PopKd - degustação, display, incentivo, treinamento.
A15: Reserva de contingência (giro garantido) | B15: =Resumo!B13*B10 | C15: Provisão | D15: Não é desembolso garantido - crédito/troca reservado se algum SKU reforçado não girar em 90 dias.
A17: Total provisionado | B17: =SUM(B13:B15)
A18: % sobre o aporte de R$ 450 mil | B18: =B17/Resumo!B13
